Workbook

Sheet Данные для расчета
A1: Вспомогательные данные для расчета сметы
A2: Накладные расходы, в % от ЗП | B2: 0.7
A3: Нормативная прибыль, в % от ЗП | B3: 0.1
A4: Накладные расходы, в % от затрат на эксплуатацию машин | B4: 0.78
A5: Нормативная прибыль прибыль в % от затрат на эксплуатацию машин | B5: 0.3
A7: НДС | B7: 0.22
A9: Расчет коэффициента для Татарстана
A10: Среднемесячная заработная плата январь-декабрь, г. Москва | B10: 180861.1 | C10: https://www.fedstat.ru/indicator/57824
A11: Среднемесячная заработная плата январь-декабрь, Республика Татарстан | B11: 90515 | C11: https://www.fedstat.ru/indicator/57824
A12: Коэффициент | B12: =ROUND(B10/B11,3) -> 1.998
A14: Примечания к расчёту
A15: • Объект: МБОУ "Физико-математический лицей №123". Система: СКУД + домофония.
A16: • Источник состава и количеств: Оборудование_1.xlsx, лист «МБОУ "Физико-математический лиц», колонки E–L (блок «Скуд»), строки 3–38.
A17: • Дубли листа оборудования суммированы по указанию заказчика: ИВЭПР 12/2 RSR3 2х7-Р БР (стр. 23 + 37) = 10 шт.; пульт PERCo-H-06/4 (стр. 22 + 27) = 4 шт.
A18: • Нормативная база: СН-2012, сборники 1, 21, 22, 24. Уровень цен — по сборникам.
A19: • Коэффициент перехода в уровень РТ (B12) применяется только к ЗП и ЗПМ. МР и ЭМ без ЗПМ не пересчитываются.
A20: • НР и НП начисляются раздельно: от ЗП (B2, B3) и от ЭМ / ЗПМ (B4, B5).
A21: • Строки с прочерком в колонке F ("Расценка не требуется") оставлены в расчёте намеренно: обоснование отсутствия расценки — в колонке I. Итоги по ним = 0.
A22: ! ВНИМАНИЕ. Поз. 28 и 29 (домофония Hikvision) посчитаны по расценкам-аналогам 22-2203-142-1/1 и 22-2203-143-1/1. Расценок на домофоны в сборниках 18/21/22/24 нет. Совпадение составов неполное — см. колонку I.
A23: ! ОТКРЫТО. Поз. 17 «Стойка с электромагнитным УБ, крайняя» (PERCo-BH02 2-04/EL, 2 шт.) — содержит электромагнит, кандидат на 21-2303-27-5/1. Сейчас прочерк.
A24: ! ОТКРЫТО. Поз. 15 «Комплект створок ограждения с магнитным УБ» (2 шт.) — расценки на ТО ограждений СКУД в сборниках 18/21/22/24 отсутствуют. Сейчас прочерк.
A25: • Цена сборника 1 (1-2203-51-1/1, ТО сетевого контроллера) взята из файла «СКУД_Лето_13_07_2026_От_Розы.xlsx». Расценки 1-2201-49-1/1 и 1-2203-32-1/1 из расчёта исключены.
... A31: ! ПРОВЕРИТЬ. Поз. 9 (кнопка выхода, 38 шт.): в листе оборудования модель и производитель не указаны. Периодичность 1 раз в год и выбор расценки 21-2301-15-1/1 (технический осмотр) приняты по паспорту РусГард. При подтверждении контактного (не сенсорного) исполнения допустим возврат на 21-2303-15-1/1 (ТО) при J=1. Разбор — в колонке I.

Sheet СКУД СН-2012 расчёт
B1: СКУД + домофония. МБОУ "Физико-математический лицей №123" | O1: Расчет в сметных нормативах сборника СН-2012 | AC1: Расчет с учетом корректировки ЗТР в уровень РТ
A2: план | B2: Наименование оборудования | C2: Тип оборудования | D2: Производитель оборудования | E2: Наименование мероприятия | F2: Шифр расценки | G2: Наименование расценки | H2: периодичность операции | I2: обоснование периодичности | J2: количество операций в год | K2: количество оборудования | L2: выполнений в год | M2: ед. измер. (на какой объем оборудования рассчитана расценка) | N2: Всего ед. измер. | O2: Цена на единицу измерения: ЗП | P2: Цена на ед. мзмерения: ЭМ | Q2: в том числе оплата труда машинистов | R2: Цена на ед. измер.: МР | S2: Поправочный коэффициент | T2: Всего ЗП: | U2: Всего: ЭМ | V2: в том числе ЗПМ | W2: Всего МР: | X2: НР | Y2: НП | Z2: Итого в год (без НДС) | AA2: НДС | AB2: Итого в год (с НДС) | AC2: Цена на единицу измерения: ЗП | AD2: Цена на ед. мзмерения: ЭМ | AE2: в том числе оплата труда машинистов | AF2: Цена на ед. измер.: МР | AG2: Всего ЗП: | AH2: Всего: ЭМ | AI2: в том числе ЗПМ | AJ2: Всего МР: | AK2: НР | AL2: НП | AM2: Итого в год (без НДС) | AN2: НДС | AO2: Итого в год (с НДС) | AP2: Справочно: затраты труда человеко-часов (на ед. измерения) | AQ2: Справочно: затраты труда человеко-часов (Общее за год)
B3: РАЗДЕЛ А. СИСТЕМА КОНТРОЛЯ И УПРАВЛЕНИЯ ДОСТУПОМ
A4: 1 | B4: Сервер СКУД | C4: СКУД LTV | D4: LTV | E4: Техническое обслуживание сервера СКУД с ПО | F4: 22-2203-113-1/1 | G4: Техническое обслуживание аппаратуры программно-аппаратного комплекса "Стрелец-Мониторинг", рабочее место администратора - ежемесячное | H4: раз в 1 мес. | I4: Периодичность учтена в наименовании расценки ("ежемесячное"). Применена по аналогии: сервер с ПО и ИБП; состав работ совпадает (проверка перехода на батареи UPS, очистка оборудования, проверка разъёмов и сетевых соединений, подтяжка соединителей, обновление ПО с перезагрузкой ПК) | J4: 12 | K4: 1 | L4: =K4*J4 -> 12 | M4: 1 | N4: =IFERROR(L4/M4,0) -> 12 | O4: 362.26 | P4: 0 | Q4: 0 | R4: 0.15 | S4: 1 | T4: =O4*N4*S4 -> 4347.12 | U4: =P4*N4*S4 -> 0 | V4: =Q4*N4*S4 -> 0 | W4: =R4*N4 -> 1.8 | X4: =T4*'Данные для расчета'!$B$2+U4*'Данные для расчета'!$B$4 -> 3042.984 | Y4: =T4*'Данные для расчета'!$B$3+V4*'Данные для расчета'!$B$5 -> 434.712 | Z4: =T4+U4+W4+X4+Y4 -> 7826.616 | AA4: =ROUND(Z4*'Данные для расчета'!$B$7,2) -> 1721.86 | AB4: =Z4+AA4 -> 9548.476 | AC4: =O4/'Данные для расчета'!$B$12 -> 181.31131 | AD4: =P4-Q4+AE4 -> 0 | AE4: =Q4/'Данные для расчета'!$B$12 -> 0 | AF4: =R4 -> 0.15 | AG4: =AC4*$N4*$S4 -> 2175.7357 | AH4: =AD4*$N4*$S4 -> 0 | AI4: =AE4*$N4*$S4 -> 0 | AJ4: =AF4*$N4 -> 1.8 | AK4: =AG4*'Данные для расчета'!$B$2+AI4*'Данные для расчета'!$B$4 -> 1523.015 | AL4: =AG4*'Данные для расчета'!$B$3+AI4*'Данные для расчета'!$B$5 -> 217.57357 | AM4: =AG4+AH4+AJ4+AK4+AL4 -> 3918.1243 | AN4: =ROUND(AM4*'Данные для расчета'!$B$7,2) -> 861.99 | AO4: =AM4+AN4 -> 4780.1143 | AP4: 0.52 | AQ4: =N4*AP4 -> 6.24
A5: 2 | B5: ИБП | C5: Skat-UPS 1500 Rack | D5: Бастион | E5: Техническое обслуживание источника бесперебойного питания | F5: 21-2203-41-1/1 | G5: Техническое обслуживание источника бесперебойного питания (ИБП) типа APC Smart UPS SRT 6 кВА стоечного исполнения - полугодовое | H5: раз в 6 мес. | I5: Паспорт | J5: 2 | K5: 1 | L5: =K5*J5 -> 2 | M5: 1 | N5: =IFERROR(L5/M5,0) -> 2 | O5: 2116.73 | P5: 1.18 | Q5: 0.01 | R5: 0 | S5: 1 | T5: =O5*N5*S5 -> 4233.46 | U5: =P5*N5*S5 -> 2.36 | V5: =Q5*N5*S5 -> 0.02 | W5: =R5*N5 -> 0 | X5: =T5*'Данные для расчета'!$B$2+U5*'Данные для расчета'!$B$4 -> 2965.2628 | Y5: =T5*'Данные для расчета'!$B$3+V5*'Данные для расчета'!$B$5 -> 423.352 | Z5: =T5+U5+W5+X5+Y5 -> 7624.4348 | AA5: =ROUND(Z5*'Данные для расчета'!$B$7,2) -> 1677.38 | AB5: =Z5+AA5 -> 9301.8148 | AC5: =O5/'Данные для расчета'!$B$12 -> 1059.4244 | AD5: =P5-Q5+AE5 -> 1.175005 | AE5: =Q5/'Данные для расчета'!$B$12 -> 0.005005005 | AF5: =R5 -> 0 | AG5: =AC5*$N5*$S5 -> 2118.8488 | AH5: =AD5*$N5*$S5 -> 2.35001 | AI5: =AE5*$N5*$S5 -> 0.01001001 | AJ5: =AF5*$N5 -> 0 | AK5: =AG5*'Данные для расчета'!$B$2+AI5*'Данные для расчета'!$B$4 -> 1483.202 | AL5: =AG5*'Данные для расчета'!$B$3+AI5*'Данные для расчета'!$B$5 -> 211.88789 | AM5: =AG5+AH5+AJ5+AK5+AL5 -> 3816.2887 | AN5: =ROUND(AM5*'Данные для расчета'!$B$7,2) -> 839.58 | AO5: =AM5+AN5 -> 4655.8687 | AP5: 2.62 | AQ5: =N5*AP5 -> 5.24
A6: 3 | B6: Контроллер СКУД с импульсным БП на 2,5 А, пластиковый корпус | C6: CS-102-CE-B | D6: RusGuard | E6: Техническое обслуживание контроллера | F6: 1-2203-51-1/1 | G6: Техническое обслуживание сетевого контроллера исполнительных устройств "СКИУ-01" | H6: раз в 1 год | I6: Паспорт RusGuard, п. 4: "В профилактических целях рекомендуется ежегодно проводить..." | J6: 1 | K6: 38 | L6: =K6*J6 -> 38 | M6: 1 | N6: =IFERROR(L6/M6,0) -> 38 | O6: 260.76 | P6: 55.13 | Q6: 33.23 | R6: 9.78 | S6: 0.7 | T6: =O6*N6*S6 -> 6936.216 | U6: =P6*N6*S6 -> 1466.458 | V6: =Q6*N6*S6 -> 883.918 | W6: =R6*N6 -> 371.64 | X6: =T6*'Данные для расчета'!$B$2+U6*'Данные для расчета'!$B$4 -> 5999.1884 | Y6: =T6*'Данные для расчета'!$B$3+V6*'Данные для расчета'!$B$5 -> 958.797 | Z6: =T6+U6+W6+X6+Y6 -> 15732.299 | AA6: =ROUND(Z6*'Данные для расчета'!$B$7,2) -> 3461.11 | AB6: =Z6+AA6 -> 19193.409 | AC6: =O6/'Данные для расчета'!$B$12 -> 130.51051 | AD6: =P6-Q6+AE6 -> 38.531632 | AE6: =Q6/'Данные для расчета'!$B$12 -> 16.631632 | AF6: =R6 -> 9.78 | AG6: =AC6*$N6*$S6 -> 3471.5796 | AH6: =AD6*$N6*$S6 -> 1024.9414 | AI6: =AE6*$N6*$S6 -> 442.4014 | AJ6: =AF6*$N6 -> 371.64 | AK6: =AG6*'Данные для расчета'!$B$2+AI6*'Данные для расчета'!$B$4 -> 2775.1788 | AL6: =AG6*'Данные для расчета'!$B$3+AI6*'Данные для расчета'!$B$5 -> 479.87838 | AM6: =AG6+AH6+AJ6+AK6+AL6 -> 8123.2182 | AN6: =ROUND(AM6*'Данные для расчета'!$B$7,2) -> 1787.11 | AO6: =(AM6+AN6) -> 9910.3282 | AP6: 0.35 | AQ6: =N6*AP6 -> 13.3
A7: 4 | B7: Считыватель настольный, USB, NFC/BLE | C7: R5-USB Prof | D7: RusGuard | E7: Техническое обслуживание считывателя | F7: 24-2003-1-3/1 | G7: Техническое обслуживание кассового оборудования, считыватель карт настольный - ежемесячное | H7: раз в 1 год | I7: Паспорт | J7: 1 | K7: 4 | L7: =K7*J7 -> 4 | M7: 1 | N7: =IFERROR(L7/M7,0) -> 4 | O7: 116.69 | P7: 0 | Q7: 0 | R7: 2.02 | S7: 1 | T7: =O7*N7*S7 -> 466.76 | U7: =P7*N7*S7 -> 0 | V7: =Q7*N7*S7 -> 0 | W7: =R7*N7 -> 8.08 | X7: =T7*'Данные для расчета'!$B$2+U7*'Данные для расчета'!$B$4 -> 326.732 | Y7: =T7*'Данные для расчета'!$B$3+V7*'Данные для расчета'!$B$5 -> 46.676 | Z7: =T7+U7+W7+X7+Y7 -> 848.248 | AA7: =ROUND(Z7*'Данные для расчета'!$B$7,2) -> 186.61 | AB7: =Z7+AA7 -> 1034.858 | AC7: =O7/'Данные для расчета'!$B$12 -> 58.403403 | AD7: =P7-Q7+AE7 -> 0 | AE7: =Q7/'Данные для расчета'!$B$12 -> 0 | AF7: =R7 -> 2.02 | AG7: =AC7*$N7*$S7 -> 233.61361 | AH7: =AD7*$N7*$S7 -> 0 | AI7: =AE7*$N7*$S7 -> 0 | AJ7: =AF7*$N7 -> 8.08 | AK7: =AG7*'Данные для расчета'!$B$2+AI7*'Данные для расчета'!$B$4 -> 163.52953 | AL7: =AG7*'Данные для расчета'!$B$3+AI7*'Данные для расчета'!$B$5 -> 23.361361 | AM7: =AG7+AH7+AJ7+AK7+AL7 -> 428.5845 | AN7: =ROUND(AM7*'Данные для расчета'!$B$7,2) -> 94.29 | AO7: =AM7+AN7 -> 522.8745 | AP7: 0.18 | AQ7: =N7*AP7 -> 0.72
A8: 5 | B8: Считыватель NFC/BLE, EM-Marin, Mifare, память 1500, IP67 | C8: R15-Multi | D8: RusGuard | E8: Техническое обслуживание считывателя | F8: 24-2903-5-1/1 | G8: Техническое обслуживание считывателя карт настенного системы контроля доступа - ежемесячное | H8: раз в 1 год | I8: Паспорт | J8: 1 | K8: 68 | L8: =K8*J8 -> 68 | M8: 1 | N8: =IFERROR(L8/M8,0) -> 68 | O8: 90.76 | P8: 0 | Q8: 0 | R8: 2.02 | S8: 1 | T8: =O8*N8*S8 -> 6171.68 | U8: =P8*N8*S8 -> 0 | V8: =Q8*N8*S8 -> 0 | W8: =R8*N8 -> 137.36 | X8: =T8*'Данные для расчета'!$B$2+U8*'Данные для расчета'!$B$4 -> 4320.176 | Y8: =T8*'Данные для расчета'!$B$3+V8*'Данные для расчета'!$B$5 -> 617.168 | Z8: =T8+U8+W8+X8+Y8 -> 11246.384 | AA8: =ROUND(Z8*'Данные для расчета'!$B$7,2) -> 2474.2 | AB8: =Z8+AA8 -> 13720.584 | AC8: =O8/'Данные для расчета'!$B$12 -> 45.425425 | AD8: =P8-Q8+AE8 -> 0 | AE8: =Q8/'Данные для расчета'!$B$12 -> 0 | AF8: =R8 -> 2.02 | AG8: =AC8*$N8*$S8 -> 3088.9289 | AH8: =AD8*$N8*$S8 -> 0 | AI8: =AE8*$N8*$S8 -> 0 | AJ8: =AF8*$N8 -> 137.36 | AK8: =AG8*'Данные для расчета'!$B$2+AI8*'Данные для расчета'!$B$4 -> 2162.2503 | AL8: =AG8*'Данные для расчета'!$B$3+AI8*'Данные для расчета'!$B$5 -> 308.89289 | AM8: =AG8+AH8+AJ8+AK8+AL8 -> 5697.4321 | AN8: =ROUND(AM8*'Данные для расчета'!$B$7,2) -> 1253.44 | AO8: =AM8+AN8 -> 6950.8721 | AP8: 0.14 | AQ8: =N8*AP8 -> 9.52
A9: 7 | B9: Замок электромагнитный (белый) | C9: AL-300Premium (белый) | D9: AccordTec | E9: Регулировка зазоров, проверка срабатывания, очистка рабочих поверхностей | F9: 21-2303-27-5/1 | G9: Техническое обслуживание электрических аппаратов до 1000 В, реле электромагнитное постоянного и переменного тока | H9: раз в 6 мес. | I9: Паспорт, п. 6.3: "Рекомендуется не реже одного раза в шесть месяцев проводить регулировку величины ЗАЗОРОВ, проверку надёжности срабатывания замка и состояния рабочих поверхностей" | J9: 2 | K9: 38 | L9: =K9*J9 -> 76 | M9: 1 | N9: =IFERROR(L9/M9,0) -> 76 | O9: 244.77 | P9: 0 | Q9: 0 | R9: 0 | S9: 1 | T9: =O9*N9*S9 -> 18602.52 | U9: =P9*N9*S9 -> 0 | V9: =Q9*N9*S9 -> 0 | W9: =R9*N9 -> 0 | X9: =T9*'Данные для расчета'!$B$2+U9*'Данные для расчета'!$B$4 -> 13021.764 | Y9: =T9*'Данные для расчета'!$B$3+V9*'Данные для расчета'!$B$5 -> 1860.252 | Z9: =T9+U9+W9+X9+Y9 -> 33484.536 | AA9: =ROUND(Z9*'Данные для расчета'!$B$7,2) -> 7366.6 | AB9: =Z9+AA9 -> 40851.136 | AC9: =O9/'Данные для расчета'!$B$12 -> 122.50751 | AD9: =P9-Q9+AE9 -> 0 | AE9: =Q9/'Данные для расчета'!$B$12 -> 0 | AF9: =R9 -> 0 | AG9: =AC9*$N9*$S9 -> 9310.5706 | AH9: =AD9*$N9*$S9 -> 0 | AI9: =AE9*$N9*$S9 -> 0 | AJ9: =AF9*$N9 -> 0 | AK9: =AG9*'Данные для расчета'!$B$2+AI9*'Данные для расчета'!$B$4 -> 6517.3994 | AL9: =AG9*'Данные для расчета'!$B$3+AI9*'Данные для расчета'!$B$5 -> 931.05706 | AM9: =AG9+AH9+AJ9+AK9+AL9 -> 16759.027 | AN9: =ROUND(AM9*'Данные для расчета'!$B$7,2) -> 3686.99 | AO9: =AM9+AN9 -> 20446.017 | AP9: 0.46 | AQ9: =N9*AP9 -> 34.96
A10: 9 | B10: Кнопка "ВЫХОД" | C10: — | D10: — | E10: Технический осмотр кнопки выхода | F10: 21-2303-15-1/1 | G10: Технический осмотр кнопки управления, число кнопок до 4 | H10: раз в 1 год | I10: Паспорт кнопки выхода (АО «РусГард»), разд. 6 «Техническое обслуживание»: «Кнопка не нуждается в обязательном техническом обслуживании. В профилактических целях рекомендуется ежегодно проводить следующие мероприятия: визуальный контроль целостности корпуса; при необходимости – чистку корпуса кнопки от грязи и пыли». Периодичность 1 раз в год — по паспорту. Состав работ по расценке приведён не в таблице, а в технической части Сборника 21, п. 1.5.1 (общий состав для раздела 1 отдела 23 «Электрические аппараты и приборы»): проверка соответствия условиям эксплуатации и нагрузки; ОЧИСТКА ОТ ПЫЛИ И ГРЯЗИ; проверка исправности подключенной электропроводки и сетей заземления; ОСМОТР И ЛИКВИДАЦИЯ ВИДИМЫХ ПОВРЕЖДЕНИЙ; затяжка крепёжных деталей; проверка исправности арматуры; проверка наличия соответствующих надписей. Два выделенных пункта дословно соответствуют паспорту. Измеритель: 10 кнопок. Принято исполнение «число кнопок до 4» (кнопка одиночная). Отклонена расценка 21-2303-15-1/1 (ТО кнопки управления, применялась в версиях v1–v1_5): её состав по п. 1.5.2 технической части Сборника 21 — частичная разборка, очистка и промывка механических и контактных деталей, опиловка, зачистка и шлифовка всех контактных поверхностей, проверка и регулировка плотности включения контактов — то есть объём капитального характера, которого паспорт не требует. ПРОВЕРИТЬ: в листе оборудования модель и производитель кнопки не указаны (прочерк). Если кнопка сенсорная (напр. РусГард RG-Btn-R35), работы с контактными поверхностями неприменимы конструктивно; если контактная — вариант 21-2303-15-1/1 при J=1 также допустим. | J10: 1 | K10: 38 | L10: =K10*J10 -> 38 | M10: 10 | N10: =IFERROR(L10/M10,0) -> 3.8 | O10: 194.48 | P10: 0 | Q10: 0 | R10: 0 | S10: 1 | T10: =O10*N10*S10 -> 739.024 | U10: =P10*N10*S10 -> 0 | V10: =Q10*N10*S10 -> 0 | W10: =R10*N10 -> 0 | X10: =T10*'Данные для расчета'!$B$2+U10*'Данные для расчета'!$B$4 -> 517.3168 | Y10: =T10*'Данные для расчета'!$B$3+V10*'Данные для расчета'!$B$5 -> 73.9024 | Z10: =T10+U10+W10+X10+Y10 -> 1330.2432 | AA10: =ROUND(Z10*'Данные для расчета'!$B$7,2) -> 292.65 | AB10: =Z10+AA10 -> 1622.8932 | AC10: =O10/'Данные для расчета'!$B$12 -> 97.337337 | AD10: =P10-Q10+AE10 -> 0 | AE10: =Q10/'Данные для расчета'!$B$12 -> 0 | AF10: =R10 -> 0 | AG10: =AC10*$N10*$S10 -> 369.88188 | AH10: =AD10*$N10*$S10 -> 0 | AI10: =AE10*$N10*$S10 -> 0 | AJ10: =AF10*$N10 -> 0 | AK10: =AG10*'Данные для расчета'!$B$2+AI10*'Данные для расчета'!$B$4 -> 258.91732 | AL10: =AG10*'Данные для расчета'!$B$3+AI10*'Данные для расчета'!$B$5 -> 36.988188 | AM10: =AG10+AH10+AJ10+AK10+AL10 -> 665.78739 | AN10: =ROUND(AM10*'Данные для расчета'!$B$7,2) -> 146.47 | AO10: =AM10+AN10 -> 812.25739 | AP10: 0.01 | AQ10: =N10*AP10 -> 0.038
A11: 10 | B11: Устройство разблокировки двери с восстанавливаемой вставкой | C11: ЛКД-УРД-1 | D11: ЛКД | E11: Техническое обслуживание устройства разблокировки | F11: 22-2203-98-1/1 | G11: Извещатель пожарный ручной тип WR7, техническое обслуживание | H11: раз в 6 мес. | I11: ПКМ. РАСЦЕНКА-АНАЛОГ. Прямой расценки на устройство разблокировки двери в сборниках 18/21/22/24 нет. Совпадает: неадресное ручное устройство под крышкой; отключение выходов ППК и исполнительных устройств перед проверкой (у УРД — развязка электромагнитного замка, иначе дверь откроется) и последующее восстановление выходов; проверка специального стекла (у УРД — восстанавливаемая вставка, тот же одноразово-восстанавливаемый приводной элемент); внешний осмотр и очистка корпуса; запись в журнал. Не совпадает: у УРД нет пломбы в составе расценки. Отклонены: 1-2203-32-1/1 (ИПР513-3А) и 22-2203-99-1/1 (FT 513) — адресные, с электроникой и проверкой шлейфов, которых у УРД нет; 22-2203-97-1/1 (FP-2) — только осмотр корпуса и светоиндикатора, без развязки замка и работы с приводным элементом; 21-2303-15-1/1 — в сборнике не приведён состав работ; 21-2303-27-9/1 — состав про аппарат в шкафу (чистка контактов, настройка уставок). | J11: 2 | K11: 59 | L11: =K11*J11 -> 118 | M11: 1 | N11: =IFERROR(L11/M11,0) -> 118 | O11: 230.96 | P11: 13.78 | Q11: 8.31 | R11: 0.43 | S11: 1 | T11: =O11*N11*S11 -> 27253.28 | U11: =P11*N11*S11 -> 1626.04 | V11: =Q11*N11*S11 -> 980.58 | W11: =R11*N11 -> 50.74 | X11: =T11*'Данные для расчета'!$B$2+U11*'Данные для расчета'!$B$4 -> 20345.607 | Y11: =T11*'Данные для расчета'!$B$3+V11*'Данные для расчета'!$B$5 -> 3019.502 | Z11: =T11+U11+W11+X11+Y11 -> 52295.169 | AA11: =ROUND(Z11*'Данные для расчета'!$B$7,2) -> 11504.94 | AB11: =Z11+AA11 -> 63800.109 | AC11: =O11/'Данные для расчета'!$B$12 -> 115.5956 | AD11: =P11-Q11+AE11 -> 9.6291592 | AE11: =Q11/'Данные для расчета'!$B$12 -> 4.1591592 | AF11: =R11 -> 0.43 | AG11: =AC11*$N11*$S11 -> 13640.28 | AH11: =AD11*$N11*$S11 -> 1136.2408 | AI11: =AE11*$N11*$S11 -> 490.78078 | AJ11: =AF11*$N11 -> 50.74 | AK11: =AG11*'Данные для расчета'!$B$2+AI11*'Данные для расчета'!$B$4 -> 9931.0052 | AL11: =AG11*'Данные для расчета'!$B$3+AI11*'Данные для расчета'!$B$5 -> 1511.2623 | AM11: =AG11+AH11+AJ11+AK11+AL11 -> 26269.529 | AN11: =ROUND(AM11*'Данные для расчета'!$B$7,2) -> 5779.3 | AO11: =AM11+AN11 -> 32048.829 | AP11: 0.31 | AQ11: =N11*AP11 -> 36.58
A12: 11 | B12: 24-портовый Ethernet-коммутатор | C12: LTV-3S24G4C-P | D12: LTV | E12: Техническое обслуживание коммутатора | F12: 22-2103-37-1/1 | G12: Техническое обслуживание IP-шлюза - ежемесячное | H12: раз в 1 мес. | I12: ПКМ. Применена по аналогии (активное сетевое оборудование). Измеритель: 10 шт. | J12: 12 | K12: 5 | L12: =K12*J12 -> 60 | M12: 10 | N12: =IFERROR(L12/M12,0) -> 6 | O12: 453.79 | P12: 0.77 | Q12: 0.01 | R12: 0 | S12: 1 | T12: =O12*N12*S12 -> 2722.74 | U12: =P12*N12*S12 -> 4.62 | V12: =Q12*N12*S12 -> 0.06 | W12: =R12*N12 -> 0 | X12: =T12*'Данные для расчета'!$B$2+U12*'Данные для расчета'!$B$4 -> 1909.5216 | Y12: =T12*'Данные для расчета'!$B$3+V12*'Данные для расчета'!$B$5 -> 272.292 | Z12: =T12+U12+W12+X12+Y12 -> 4909.1736 | AA12: =ROUND(Z12*'Данные для расчета'!$B$7,2) -> 1080.02 | AB12: =Z12+AA12 -> 5989.1936 | AC12: =O12/'Данные для расчета'!$B$12 -> 227.12212 | AD12: =P12-Q12+AE12 -> 0.76500501 | AE12: =Q12/'Данные для расчета'!$B$12 -> 0.005005005 | AF12: =R12 -> 0 | AG12: =AC12*$N12*$S12 -> 1362.7327 | AH12: =AD12*$N12*$S12 -> 4.59003 | AI12: =AE12*$N12*$S12 -> 0.03003003 | AJ12: =AF12*$N12 -> 0 | AK12: =AG12*'Данные для расчета'!$B$2+AI12*'Данные для расчета'!$B$4 -> 953.93634 | AL12: =AG12*'Данные для расчета'!$B$3+AI12*'Данные для расчета'!$B$5 -> 136.28228 | AM12: =AG12+AH12+AJ12+AK12+AL12 -> 2457.5414 | AN12: =ROUND(AM12*'Данные для расчета'!$B$7,2) -> 540.66 | AO12: =AM12+AN12 -> 2998.2014 | AP12: 0.7 | AQ12: =N12*AP12 -> 4.2
A13: 12 | B13: Модуль сопряжения (преобразователь интерфейса) | C13: R3-MC-1 | D13: Рубеж | E13: Техническое обслуживание модуля сопряжения (преобразователя интерфейсов) | F13: 22-2203-146-2/1 | G13: Техническое обслуживание приборов охранно-пожарной сигнализации на базе оборудования С2000, преобразователь интерфейсов С2000-USB - годовое | H13: раз в 6 мес. | I13: Паспорт | J13: 2 | K13: 1 | L13: =K13*J13 -> 2 | M13: 1 | N13: =IFERROR(L13/M13,0) -> 2 | O13: 90.76 | P13: 0 | Q13: 0 | R13: 4.44 | S13: 1 | T13: =O13*N13*S13 -> 181.52 | U13: =P13*N13*S13 -> 0 | V13: =Q13*N13*S13 -> 0 | W13: =R13*N13 -> 8.88 | X13: =T13*'Данные для расчета'!$B$2+U13*'Данные для расчета'!$B$4 -> 127.064 | Y13: =T13*'Данные для расчета'!$B$3+V13*'Данные для расчета'!$B$5 -> 18.152 | Z13: =T13+U13+W13+X13+Y13 -> 335.616 | AA13: =ROUND(Z13*'Данные для расчета'!$B$7,2) -> 73.84 | AB13: =Z13+AA13 -> 409.456 | AC13: =O13/'Данные для расчета'!$B$12 -> 45.425425 | AD13: =P13-Q13+AE13 -> 0 | AE13: =Q13/'Данные для расчета'!$B$12 -> 0 | AF13: =R13 -> 4.44 | AG13: =AC13*$N13*$S13 -> 90.850851 | AH13: =AD13*$N13*$S13 -> 0 | AI13: =AE13*$N13*$S13 -> 0 | AJ13: =AF13*$N13 -> 8.88 | AK13: =AG13*'Данные для расчета'!$B$2+AI13*'Данные для расчета'!$B$4 -> 63.595596 | AL13: =AG13*'Данные для расчета'!$B$3+AI13*'Данные для расчета'!$B$5 -> 9.0850851 | AM13: =AG13+AH13+AJ13+AK13+AL13 -> 172.41153 | AN13: =ROUND(AM13*'Данные для расчета'!$B$7,2) -> 37.93 | AO13: =AM13+AN13 -> 210.34153 | AP13: 0.14 | AQ13: =N13*AP13 -> 0.28
A14: 13 | B14: Тумбовый турникет-трипод с автоматическими планками "Антипаника" и пультом управления | C14: PERCo-TTD-10AB | D14: PERCo | E14: Техническое обслуживание турникета | F14: 24-2903-7-3/1 | G14: Техническое обслуживание полноростовых роторных турникетов серии ПерКо RTD-15.2 с механическим приводом доворота створок, расположенных в зданиях многофункционального центра трудовой миграции - годовое | H14: раз в 1 год | I14: Паспорт | J14: 1 | K14: 2 | L14: =K14*J14 -> 2 | M14: 1 | N14: =IFERROR(L14/M14,0) -> 2 | O14: 3540.15 | P14: 0.44 | Q14: 0 | R14: 186.84 | S14: 1 | T14: =O14*N14*S14 -> 7080.3 | U14: =P14*N14*S14 -> 0.88 | V14: =Q14*N14*S14 -> 0 | W14: =R14*N14 -> 373.68 | X14: =T14*'Данные для расчета'!$B$2+U14*'Данные для расчета'!$B$4 -> 4956.8964 | Y14: =T14*'Данные для расчета'!$B$3+V14*'Данные для расчета'!$B$5 -> 708.03 | Z14: =T14+U14+W14+X14+Y14 -> 13119.786 | AA14: =ROUND(Z14*'Данные для расчета'!$B$7,2) -> 2886.35 | AB14: =Z14+AA14 -> 16006.136 | AC14: =O14/'Данные для расчета'!$B$12 -> 1771.8468 | AD14: =P14-Q14+AE14 -> 0.44 | AE14: =Q14/'Данные для расчета'!$B$12 -> 0 | AF14: =R14 -> 186.84 | AG14: =AC14*$N14*$S14 -> 3543.6937 | AH14: =AD14*$N14*$S14 -> 0.88 | AI14: =AE14*$N14*$S14 -> 0 | AJ14: =AF14*$N14 -> 373.68 | AK14: =AG14*'Данные для расчета'!$B$2+AI14*'Данные для расчета'!$B$4 -> 2480.5856 | AL14: =AG14*'Данные для расчета'!$B$3+AI14*'Данные для расчета'!$B$5 -> 354.36937 | AM14: =AG14+AH14+AJ14+AK14+AL14 -> 6753.2086 | AN14: =ROUND(AM14*'Данные для расчета'!$B$7,2) -> 1485.71 | AO14: =AM14+AN14 -> 8238.9186 | AP14: 5.8 | AQ14: =N14*AP14 -> 11.6
A15: 21 | B15: Блок питания | C15: ИВЭПР 12/2 RSR3 2х7-Р БР | D15: Бастион | E15: Технический осмотр источника вторичного электропитания | F15: 22-2201-78-1/1 | G15: Технический осмотр источника вторичного электропитания типа ИВЭП 112-0,3-1 "Астра-БП1" | H15: раз в 1 мес. | I15: ПКМ | J15: 10 | K15: 10 | L15: =K15*J15 -> 100 | M15: 1 | N15: =IFERROR(L15/M15,0) -> 100 | O15: 62.7 | P15: 0 | Q15: 0 | R15: 3.38 | S15: 1 | T15: =O15*N15*S15 -> 6270 | U15: =P15*N15*S15 -> 0 | V15: =Q15*N15*S15 -> 0 | W15: =R15*N15 -> 338 | X15: =T15*'Данные для расчета'!$B$2+U15*'Данные для расчета'!$B$4 -> 4389 | Y15: =T15*'Данные для расчета'!$B$3+V15*'Данные для расчета'!$B$5 -> 627 | Z15: =T15+U15+W15+X15+Y15 -> 11624 | AA15: =ROUND(Z15*'Данные для расчета'!$B$7,2) -> 2557.28 | AB15: =Z15+AA15 -> 14181.28 | AC15: =O15/'Данные для расчета'!$B$12 -> 31.381381 | AD15: =P15-Q15+AE15 -> 0 | AE15: =Q15/'Данные для расчета'!$B$12 -> 0 | AF15: =R15 -> 3.38 | AG15: =AC15*$N15*$S15 -> 3138.1381 | AH15: =AD15*$N15*$S15 -> 0 | AI15: =AE15*$N15*$S15 -> 0 | AJ15: =AF15*$N15 -> 338 | AK15: =AG15*'Данные для расчета'!$B$2+AI15*'Данные для расчета'!$B$4 -> 2196.6967 | AL15: =AG15*'Данные для расчета'!$B$3+AI15*'Данные для расчета'!$B$5 -> 313.81381 | AM15: =AG15+AH15+AJ15+AK15+AL15 -> 5986.6486 | AN15: =ROUND(AM15*'Данные для расчета'!$B$7,2) -> 1317.06 | AO15: =AM15+AN15 -> 7303.7086 | AP15: 0.09 | AQ15: =N15*AP15 -> 9
A16: 21 | B16: Блок питания | C16: ИВЭПР 12/2 RSR3 2х7-Р БР | D16: Бастион | E16: Техническое обслуживание источника вторичного электропитания, проверка АКБ | F16: 22-2203-91-1/1 | G16: Техническое обслуживание источника вторичного электропитания типа ИВЭП 112-0,3-1 "Астра-БП1" | H16: раз в 6 мес. | I16: ПКМ | J16: 2 | K16: 10 | L16: =K16*J16 -> 20 | M16: 1 | N16: =IFERROR(L16/M16,0) -> 20 | O16: 877.77 | P16: 0 | Q16: 0 | R16: 3.38 | S16: 1 | T16: =O16*N16*S16 -> 17555.4 | U16: =P16*N16*S16 -> 0 | V16: =Q16*N16*S16 -> 0 | W16: =R16*N16 -> 67.6 | X16: =T16*'Данные для расчета'!$B$2+U16*'Данные для расчета'!$B$4 -> 12288.78 | Y16: =T16*'Данные для расчета'!$B$3+V16*'Данные для расчета'!$B$5 -> 1755.54 | Z16: =T16+U16+W16+X16+Y16 -> 31667.32 | AA16: =ROUND(Z16*'Данные для расчета'!$B$7,2) -> 6966.81 | AB16: =Z16+AA16 -> 38634.13 | AC16: =O16/'Данные для расчета'!$B$12 -> 439.32432 | AD16: =P16-Q16+AE16 -> 0 | AE16: =Q16/'Данные для расчета'!$B$12 -> 0 | AF16: =R16 -> 3.38 | AG16: =AC16*$N16*$S16 -> 8786.4865 | AH16: =AD16*$N16*$S16 -> 0 | AI16: =AE16*$N16*$S16 -> 0 | AJ16: =AF16*$N16 -> 67.6 | AK16: =AG16*'Данные для расчета'!$B$2+AI16*'Данные для расчета'!$B$4 -> 6150.5405 | AL16: =AG16*'Данные для расчета'!$B$3+AI16*'Данные для расчета'!$B$5 -> 878.64865 | AM16: =AG16+AH16+AJ16+AK16+AL16 -> 15883.276 | AN16: =ROUND(AM16*'Данные для расчета'!$B$7,2) -> 3494.32 | AO16: =AM16+AN16 -> 19377.596 | AP16: 1.26 | AQ16: =N16*AP16 -> 25.2
A17: 24 | B17: Блок питания | C17: БИРП 12-10 | D17: Бастион | E17: Технический осмотр источника вторичного электропитания | F17: 22-2201-78-1/1 | G17: Технический осмотр источника вторичного электропитания типа ИВЭП 112-0,3-1 "Астра-БП1" | H17: раз в 1 мес. | I17: ПКМ | J17: 10 | K17: 4 | L17: =K17*J17 -> 40 | M17: 1 | N17: =IFERROR(L17/M17,0) -> 40 | O17: 62.7 | P17: 0 | Q17: 0 | R17: 3.38 | S17: 1 | T17: =O17*N17*S17 -> 2508 | U17: =P17*N17*S17 -> 0 | V17: =Q17*N17*S17 -> 0 | W17: =R17*N17 -> 135.2 | X17: =T17*'Данные для расчета'!$B$2+U17*'Данные для расчета'!$B$4 -> 1755.6 | Y17: =T17*'Данные для расчета'!$B$3+V17*'Данные для расчета'!$B$5 -> 250.8 | Z17: =T17+U17+W17+X17+Y17 -> 4649.6 | AA17: =ROUND(Z17*'Данные для расчета'!$B$7,2) -> 1022.91 | AB17: =Z17+AA17 -> 5672.51 | AC17: =O17/'Данные для расчета'!$B$12 -> 31.381381 | AD17: =P17-Q17+AE17 -> 0 | AE17: =Q17/'Данные для расчета'!$B$12 -> 0 | AF17: =R17 -> 3.38 | AG17: =AC17*$N17*$S17 -> 1255.2553 | AH17: =AD17*$N17*$S17 -> 0 | AI17: =AE17*$N17*$S17 -> 0 | AJ17: =AF17*$N17 -> 135.2 | AK17: =AG17*'Данные для расчета'!$B$2+AI17*'Данные для расчета'!$B$4 -> 878.67868 | AL17: =AG17*'Данные для расчета'!$B$3+AI17*'Данные для расчета'!$B$5 -> 125.52553 | AM17: =AG17+AH17+AJ17+AK17+AL17 -> 2394.6595 | AN17: =ROUND(AM17*'Данные для расчета'!$B$7,2) -> 526.83 | AO17: =AM17+AN17 -> 2921.4895 | AP17: 0.09 | AQ17: =N17*AP17 -> 3.6
A18: 24 | B18: Блок питания | C18: БИРП 12-10 | D18: Бастион | E18: Техническое обслуживание источника вторичного электропитания | F18: 22-2203-91-1/1 | G18: Техническое обслуживание источника вторичного электропитания типа ИВЭП 112-0,3-1 "Астра-БП1" | H18: раз в 6 мес. | I18: ПКМ | J18: 2 | K18: 4 | L18: =K18*J18 -> 8 | M18: 1 | N18: =IFERROR(L18/M18,0) -> 8 | O18: 877.77 | P18: 0 | Q18: 0 | R18: 3.38 | S18: 1 | T18: =O18*N18*S18 -> 7022.16 | U18: =P18*N18*S18 -> 0 | V18: =Q18*N18*S18 -> 0 | W18: =R18*N18 -> 27.04 | X18: =T18*'Данные для расчета'!$B$2+U18*'Данные для расчета'!$B$4 -> 4915.512 | Y18: =T18*'Данные для расчета'!$B$3+V18*'Данные для расчета'!$B$5 -> 702.216 | Z18: =T18+U18+W18+X18+Y18 -> 12666.928 | AA18: =ROUND(Z18*'Данные для расчета'!$B$7,2) -> 2786.72 | AB18: =Z18+AA18 -> 15453.648 | AC18: =O18/'Данные для расчета'!$B$12 -> 439.32432 | AD18: =P18-Q18+AE18 -> 0 | AE18: =Q18/'Данные для расчета'!$B$12 -> 0 | AF18: =R18 -> 3.38 | AG18: =AC18*$N18*$S18 -> 3514.5946 | AH18: =AD18*$N18*$S18 -> 0 | AI18: =AE18*$N18*$S18 -> 0 | AJ18: =AF18*$N18 -> 27.04 | AK18: =AG18*'Данные для расчета'!$B$2+AI18*'Данные для расчета'!$B$4 -> 2460.2162 | AL18: =AG18*'Данные для расчета'!$B$3+AI18*'Данные для расчета'!$B$5 -> 351.45946 | AM18: =AG18+AH18+AJ18+AK18+AL18 -> 6353.3103 | AN18: =ROUND(AM18*'Данные для расчета'!$B$7,2) -> 1397.73 | AO18: =AM18+AN18 -> 7751.0403 | AP18: 1.26 | AQ18: =N18*AP18 -> 10.08
... A21: 27 | B21: Источник бесперебойного питания | C21: SKAT-UPS 1500 RACK+3X9Ah | D21: Бастион | E21: Техническое обслуживание источника бесперебойного питания | F21: 21-2203-41-1/1 | G21: Техническое обслуживание источника бесперебойного питания (ИБП) типа APC Smart UPS SRT 6 кВА стоечного исполнения - полугодовое | H21: раз в 6 мес. | I21: Паспорт | J21: 2 | K21: 2 | L21: =K21*J21 -> 4 | M21: 1 | N21: =IFERROR(L21/M21,0) -> 4 | O21: 2116.73 | P21: 1.18 | Q21: 0.01 | R21: 0 | S21: 1 | T21: =O21*N21*S21 -> 8466.92 | U21: =P21*N21*S21 -> 4.72 | V21: =Q21*N21*S21 -> 0.04 | W21: =R21*N21 -> 0 | X21: =T21*'Данные для расчета'!$B$2+U21*'Данные для расчета'!$B$4 -> 5930.5256 | Y21: =T21*'Данные для расчета'!$B$3+V21*'Данные для расчета'!$B$5 -> 846.704 | Z21: =T21+U21+W21+X21+Y21 -> 15248.87 | AA21: =ROUND(Z21*'Данные для расчета'!$B$7,2) -> 3354.75 | AB21: =Z21+AA21 -> 18603.62 | AC21: =O21/'Данные для расчета'!$B$12 -> 1059.4244 | AD21: =P21-Q21+AE21 -> 1.175005 | AE21: =Q21/'Данные для расчета'!$B$12 -> 0.005005005 | AF21: =R21 -> 0 | AG21: =AC21*$N21*$S21 -> 4237.6977 | AH21: =AD21*$N21*$S21 -> 4.70002 | AI21: =AE21*$N21*$S21 -> 0.02002002 | AJ21: =AF21*$N21 -> 0 | AK21: =AG21*'Данные для расчета'!$B$2+AI21*'Данные для расчета'!$B$4 -> 2966.404 | AL21: =AG21*'Данные для расчета'!$B$3+AI21*'Данные для расчета'!$B$5 -> 423.77578 | AM21: =AG21+AH21+AJ21+AK21+AL21 -> 7632.5775 | AN21: =ROUND(AM21*'Данные для расчета'!$B$7,2) -> 1679.17 | AO21: =AM21+AN21 -> 9311.7475 | AP21: 2.62 | AQ21: =N21*AP21 -> 10.48
B22: РАЗДЕЛ Б. ДОМОФОНИЯ
A23: 28 | B23: Видеодомофон | C23: DS-KH8520-WTE1 | D23: Hikvision | E23: Техническое обслуживание монитора видеодомофона | F23: 1-2301-1-1/1 | G23: Техническое обслуживание мастер-станции системы экстренной связи, настенного исполнения, с ЖК-дисплеем и 12-кнопочной клавиатурой, с функцией программирования и диагностики всей системы - ежемесячное | H23: раз в 1 мес. | I23: ПКМ | J23: 12 | K23: 4 | L23: =K23*J23 -> 48 | M23: 1 | N23: =IFERROR(L23/M23,0) -> 48 | O23: 350.16 | P23: 27.57 | Q23: 16.61 | R23: 1.93 | S23: 0.75 | T23: =O23*N23*S23 -> 12605.76 | U23: =P23*N23*S23 -> 992.52 | V23: =Q23*N23*S23 -> 597.96 | W23: =R23*N23 -> 92.64 | X23: =T23*'Данные для расчета'!$B$2+U23*'Данные для расчета'!$B$4 -> 9598.1976 | Y23: =T23*'Данные для расчета'!$B$3+V23*'Данные для расчета'!$B$5 -> 1439.964 | Z23: =T23+U23+W23+X23+Y23 -> 24729.082 | AA23: =ROUND(Z23*'Данные для расчета'!$B$7,2) -> 5440.4 | AB23: =Z23+AA23 -> 30169.482 | AC23: =O23/'Данные для расчета'!$B$12 -> 175.25526 | AD23: =P23-Q23+AE23 -> 19.273313 | AE23: =Q23/'Данные для расчета'!$B$12 -> 8.3133133 | AF23: =R23 -> 1.93 | AG23: =AC23*$N23*$S23 -> 6309.1892 | AH23: =AD23*$N23*$S23 -> 693.83928 | AI23: =AE23*$N23*$S23 -> 299.27928 | AJ23: =AF23*$N23 -> 92.64 | AK23: =AG23*'Данные для расчета'!$B$2+AI23*'Данные для расчета'!$B$4 -> 4649.8703 | AL23: =AG23*'Данные для расчета'!$B$3+AI23*'Данные для расчета'!$B$5 -> 720.7027 | AM23: =AG23+AH23+AJ23+AK23+AL23 -> 12466.241 | AN23: =ROUND(AM23*'Данные для расчета'!$B$7,2) -> 2742.57 | AO23: =AM23+AN23 -> 15208.811 | AP23: 0.47 | AQ23: =N23*AP23 -> 22.56
A24: 29 | B24: Блок вызова (в комплекте с рамкой монтажной) | C24: DS-KD8003-IME1/Surface | D24: Hikvision | E24: Техническое обслуживание блока вызова | F24: 1-2301-1-1/1 | G24: Техническое обслуживание приборов системы экстренной связи, абонентская вызывная станция в корпусе с дверцей - ежемесячное | H24: раз в 1 мес. | I24: ПКМ | J24: 0 | K24: 4 | L24: =K24*J24 -> 0 | M24: 1 | N24: =IFERROR(L24/M24,0) -> 0 | O24: 162.07 | P24: 0.11 | Q24: 0 | R24: 70.38 | S24: 0.75 | T24: =O24*N24*S24 -> 0 | U24: =P24*N24*S24 -> 0 | V24: =Q24*N24*S24 -> 0 | W24: =R24*N24 -> 0 | X24: =T24*'Данные для расчета'!$B$2+U24*'Данные для расчета'!$B$4 -> 0 | Y24: =T24*'Данные для расчета'!$B$3+V24*'Данные для расчета'!$B$5 -> 0 | Z24: =T24+U24+W24+X24+Y24 -> 0 | AA24: =ROUND(Z24*'Данные для расчета'!$B$7,2) -> 0 | AB24: =Z24+AA24 -> 0 | AC24: =O24/'Данные для расчета'!$B$12 -> 81.116116 | AD24: =P24-Q24+AE24 -> 0.11 | AE24: =Q24/'Данные для расчета'!$B$12 -> 0 | AF24: =R24 -> 70.38 | AG24: =AC24*$N24*$S24 -> 0 | AH24: =AD24*$N24*$S24 -> 0 | AI24: =AE24*$N24*$S24 -> 0 | AJ24: =AF24*$N24 -> 0 | AK24: =AG24*'Данные для расчета'!$B$2+AI24*'Данные для расчета'!$B$4 -> 0 | AL24: =AG24*'Данные для расчета'!$B$3+AI24*'Данные для расчета'!$B$5 -> 0 | AM24: =AG24+AH24+AJ24+AK24+AL24 -> 0 | AN24: =ROUND(AM24*'Данные для расчета'!$B$7,2) -> 0 | AO24: =AM24+AN24 -> 0 | AP24: 0.25 | AQ24: =N24*AP24 -> 0
A25: 31 | B25: Замок электромагнитный (белый/серый) | C25: AL-300PRemium | D25: AccordTec | E25: Регулировка зазоров, проверка срабатывания, очистка рабочих поверхностей | F25: 21-2303-27-5/1 | G25: Техническое обслуживание электрических аппаратов до 1000 В, реле электромагнитное постоянного и переменного тока | H25: раз в 6 мес. | I25: Паспорт, п. 6.3 (аналогично поз. 7) | J25: 2 | K25: 4 | L25: =K25*J25 -> 8 | M25: 1 | N25: =IFERROR(L25/M25,0) -> 8 | O25: 244.77 | P25: 0 | Q25: 0 | R25: 0 | S25: 1 | T25: =O25*N25*S25 -> 1958.16 | U25: =P25*N25*S25 -> 0 | V25: =Q25*N25*S25 -> 0 | W25: =R25*N25 -> 0 | X25: =T25*'Данные для расчета'!$B$2+U25*'Данные для расчета'!$B$4 -> 1370.712 | Y25: =T25*'Данные для расчета'!$B$3+V25*'Данные для расчета'!$B$5 -> 195.816 | Z25: =T25+U25+W25+X25+Y25 -> 3524.688 | AA25: =ROUND(Z25*'Данные для расчета'!$B$7,2) -> 775.43 | AB25: =Z25+AA25 -> 4300.118 | AC25: =O25/'Данные для расчета'!$B$12 -> 122.50751 | AD25: =P25-Q25+AE25 -> 0 | AE25: =Q25/'Данные для расчета'!$B$12 -> 0 | AF25: =R25 -> 0 | AG25: =AC25*$N25*$S25 -> 980.06006 | AH25: =AD25*$N25*$S25 -> 0 | AI25: =AE25*$N25*$S25 -> 0 | AJ25: =AF25*$N25 -> 0 | AK25: =AG25*'Данные для расчета'!$B$2+AI25*'Данные для расчета'!$B$4 -> 686.04204 | AL25: =AG25*'Данные для расчета'!$B$3+AI25*'Данные для расчета'!$B$5 -> 98.006006 | AM25: =AG25+AH25+AJ25+AK25+AL25 -> 1764.1081 | AN25: =ROUND(AM25*'Данные для расчета'!$B$7,2) -> 388.1 | AO25: =AM25+AN25 -> 2152.2081 | AP25: 0.46 | AQ25: =N25*AP25 -> 3.68
A26: 32 | B26: Источник питания | C26: ИВЭПР 12/2 RS-R3 2х7 БР | D26: Рубеж | E26: Технический осмотр источника вторичного электропитания | F26: 22-2201-78-1/1 | G26: Технический осмотр источника вторичного электропитания типа ИВЭП 112-0,3-1 "Астра-БП1" | H26: раз в 1 мес. | I26: ПКМ | J26: 10 | K26: 4 | L26: =K26*J26 -> 40 | M26: 1 | N26: =IFERROR(L26/M26,0) -> 40 | O26: 62.7 | P26: 0 | Q26: 0 | R26: 3.38 | S26: 1 | T26: =O26*N26*S26 -> 2508 | U26: =P26*N26*S26 -> 0 | V26: =Q26*N26*S26 -> 0 | W26: =R26*N26 -> 135.2 | X26: =T26*'Данные для расчета'!$B$2+U26*'Данные для расчета'!$B$4 -> 1755.6 | Y26: =T26*'Данные для расчета'!$B$3+V26*'Данные для расчета'!$B$5 -> 250.8 | Z26: =T26+U26+W26+X26+Y26 -> 4649.6 | AA26: =ROUND(Z26*'Данные для расчета'!$B$7,2) -> 1022.91 | AB26: =Z26+AA26 -> 5672.51 | AC26: =O26/'Данные для расчета'!$B$12 -> 31.381381 | AD26: =P26-Q26+AE26 -> 0 | AE26: =Q26/'Данные для расчета'!$B$12 -> 0 | AF26: =R26 -> 3.38 | AG26: =AC26*$N26*$S26 -> 1255.2553 | AH26: =AD26*$N26*$S26 -> 0 | AI26: =AE26*$N26*$S26 -> 0 | AJ26: =AF26*$N26 -> 135.2 | AK26: =AG26*'Данные для расчета'!$B$2+AI26*'Данные для расчета'!$B$4 -> 878.67868 | AL26: =AG26*'Данные для расчета'!$B$3+AI26*'Данные для расчета'!$B$5 -> 125.52553 | AM26: =AG26+AH26+AJ26+AK26+AL26 -> 2394.6595 | AN26: =ROUND(AM26*'Данные для расчета'!$B$7,2) -> 526.83 | AO26: =AM26+AN26 -> 2921.4895 | AP26: 0.09 | AQ26: =N26*AP26 -> 3.6
A27: 32 | B27: Источник питания | C27: ИВЭПР 12/2 RS-R3 2х7 БР | D27: Рубеж | E27: Техническое обслуживание источника вторичного электропитания | F27: 22-2203-91-1/1 | G27: Техническое обслуживание источника вторичного электропитания типа ИВЭП 112-0,3-1 "Астра-БП1" | H27: раз в 6 мес. | I27: ПКМ | J27: 2 | K27: 4 | L27: =K27*J27 -> 8 | M27: 1 | N27: =IFERROR(L27/M27,0) -> 8 | O27: 877.77 | P27: 0 | Q27: 0 | R27: 3.38 | S27: 1 | T27: =O27*N27*S27 -> 7022.16 | U27: =P27*N27*S27 -> 0 | V27: =Q27*N27*S27 -> 0 | W27: =R27*N27 -> 27.04 | X27: =T27*'Данные для расчета'!$B$2+U27*'Данные для расчета'!$B$4 -> 4915.512 | Y27: =T27*'Данные для расчета'!$B$3+V27*'Данные для расчета'!$B$5 -> 702.216 | Z27: =T27+U27+W27+X27+Y27 -> 12666.928 | AA27: =ROUND(Z27*'Данные для расчета'!$B$7,2) -> 2786.72 | AB27: =Z27+AA27 -> 15453.648 | AC27: =O27/'Данные для расчета'!$B$12 -> 439.32432 | AD27: =P27-Q27+AE27 -> 0 | AE27: =Q27/'Данные для расчета'!$B$12 -> 0 | AF27: =R27 -> 3.38 | AG27: =AC27*$N27*$S27 -> 3514.5946 | AH27: =AD27*$N27*$S27 -> 0 | AI27: =AE27*$N27*$S27 -> 0 | AJ27: =AF27*$N27 -> 27.04 | AK27: =AG27*'Данные для расчета'!$B$2+AI27*'Данные для расчета'!$B$4 -> 2460.2162 | AL27: =AG27*'Данные для расчета'!$B$3+AI27*'Данные для расчета'!$B$5 -> 351.45946 | AM27: =AG27+AH27+AJ27+AK27+AL27 -> 6353.3103 | AN27: =ROUND(AM27*'Данные для расчета'!$B$7,2) -> 1397.73 | AO27: =AM27+AN27 -> 7751.0403 | AP27: 1.26 | AQ27: =N27*AP27 -> 10.08
B29: ИТОГО | T29: =SUM(T4:T27) -> 148884.64 | U29: =SUM(U4:U27) -> 4099.958 | V29: =SUM(V4:V27) -> 2462.598 | W29: =SUM(W4:W27) -> 1774.9 | X29: =SUM(X4:X27) -> 107417.22 | Y29: =SUM(Y4:Y27) -> 15627.243 | Z29: =SUM(Z4:Z27) -> 277803.96 | AA29: =SUM(AA4:AA27) -> 61116.87 | AB29: =SUM(AB4:AB27) -> 338920.83 | AG29: =SUM(AG4:AG27) -> 74516.837 | AH29: =SUM(AH4:AH27) -> 2869.8915 | AI29: =SUM(AI4:AI27) -> 1232.5315 | AJ29: =SUM(AJ4:AJ27) -> 1774.9 | AK29: =SUM(AK4:AK27) -> 53123.16 | AL29: =SUM(AL4:AL27) -> 7821.4431 | AM29: =SUM(AM4:AM27) -> 140106.23 | AN29: =SUM(AN4:AN27) -> 30823.39 | AO29: =SUM(AO4:AO27) -> 170929.62 | AQ29: =SUM(AQ4:AQ27) -> 226.198

Sheet Спецификация
A1: № | B1: Наименование | C1: Марка / модель | D1: Производитель | E1: Ед. изм. | F1: Кол-во | G1: Источник: Оборудование_1.xlsx, лист «МБОУ "Физико-математический лиц», колонки E–L
A2: 1 | B2: Сервер СКУД с ПО сервера поддержки сетевых устройств | C2: СКУД LTV | D2: LTV | E2: шт | F2: 1 | G2: стр. 3
A3: 2 | B3: ИБП | C3: Skat-UPS 1500 Rack | D3: Бастион | E3: шт | F3: 1 | G3: стр. 4
A4: 3 | B4: Контроллер СКУД с импульсным БП на 2,5 А, пластиковый корпус | C4: CS-102-CE-B | D4: RusGuard | E4: шт | F4: 38 | G4: стр. 5
A5: 4 | B5: Считыватель настольный, USB, NFC/BLE | C5: R5-USB Prof | D5: RusGuard | E5: шт | F5: 4 | G5: стр. 6
A6: 5 | B6: Считыватель NFC/BLE, EM-Marin, Mifare, память 1500, IP67, корпус чёрный, накладка серого цвета | C6: R15-Multi | D6: RusGuard | E6: шт | F6: 68 | G6: стр. 7
A7: 6 | B7: Аккумуляторная батарея | C7: АКБ 7 Ач | D7: — | E7: шт | F7: 38 | G7: стр. 8
A8: 7 | B8: Замок электромагнитный (белый) | C8: AL-300Premium (белый) | D8: AccordTec | E8: шт | F8: 38 | G8: стр. 9
A9: 8 | B9: Комплект монтажа электромагнитного замка (белый) | C9: MK AL-300PR (белый) | D9: AccordTec | E9: шт | F9: 38 | G9: стр. 10
A10: 9 | B10: Кнопка «ВЫХОД» | C10: — | D10: — | E10: шт | F10: 38 | G10: стр. 11
A11: 10 | B11: Устройство разблокировки двери с восстанавливаемой вставкой | C11: ЛКД-УРД-1 | D11: ЛКД | E11: шт | F11: 59 | G11: стр. 12
A12: 11 | B12: 24-портовый Ethernet-коммутатор | C12: LTV-3S24G4C-P | D12: LTV | E12: шт | F12: 5 | G12: стр. 13
A13: 12 | B13: Модуль сопряжения | C13: R3-MC-1 | D13: Рубеж | E13: шт | F13: 1 | G13: стр. 14
... A34: 33 | B34: Аккумулятор | C34: АКБ 7 Ач | D34: ГК РУТЕК | E34: шт | F34: 8 | G34: стр. 36
B35: ИТОГО позиций | F35: =SUM(F2:F34) -> 417
